fpclib/__init__.py
fpclib-1.10.1.1.dist-info/LICENSE
fpclib-1.10.1.1.dist-info/METADATA
fpclib-1.10.1.1.dist-info/WHEEL
fpclib-1.10.1.1.dist-info/RECORD
