Metadata-Version: 2.1
Name: fpclib
Version: 1.10.1.1
Summary: A powerful library for curating games for Flashpoint.
Home-page: https://www.mathgeniuszach.com/
License: CC BY-NC-SA 4.0
Author: mathgeniuszach
Author-email: huntingmanzach@gmail.com
Requires-Python: >=3.9,<4.0
Classifier: License :: Other/Proprietary License
Classifier: Programming Language :: Python :: 3
Classifier: Programming Language :: Python :: 3.9
Classifier: Programming Language :: Python :: 3.10
Classifier: Programming Language :: Python :: 3.11
Classifier: Programming Language :: Python :: 3.12
Requires-Dist: beautifulsoup4 (>=4.12.3,<5.0.0)
Requires-Dist: pillow (>=10.3.0,<11.0.0)
Requires-Dist: requests (>=2.31.0,<3.0.0)
Requires-Dist: ruamel-yaml (==0.16.13)
Project-URL: Documentation, https://www.mathgeniuszach.com/bin/fpclib/
Project-URL: Repository, https://github.com/xMGZx/fpclib
